ansideps.py
ansideps-0.1.0.dist-info/DESCRIPTION.rst
ansideps-0.1.0.dist-info/METADATA
ansideps-0.1.0.dist-info/RECORD
ansideps-0.1.0.dist-info/WHEEL
ansideps-0.1.0.dist-info/entry_points.txt
ansideps-0.1.0.dist-info/metadata.json
ansideps-0.1.0.dist-info/top_level.txt
