Metadata-Version: 2.0
Name: ansideps
Version: 0.1.0
Summary: Resolve Ansible role relationships
Home-page: https://github.com/dhutty/ansideps
Author: Duncan Hutty
Author-email: dhutty@allgoodbits.org
License: Copyright 2017 Duncan Hutty
Requires-Dist: click
Requires-Dist: pydotplus
Requires-Dist: pyyaml
Requires-Dist: networkx
